CHANGES.txt
LICENSE.txt
MANIFEST.in
README.rst
__init__.py
_noise.h
_perlin.c
_simplex.c
perlin.py
pyproject.toml
setup.cfg
setup.py
shader.py
shader_noise.py
test.py
./__init__.py
./perlin.py
./setup.py
./shader.py
./shader_noise.py
./test.py
examples/1dnoise.py
examples/2dtexture.py
examples/animate_tex.py
examples/atmosphere.py
examples/bump.py
examples/earth.1024x512.jpg
examples/planet.py
vec_noise_numpy2.egg-info/PKG-INFO
vec_noise_numpy2.egg-info/SOURCES.txt
vec_noise_numpy2.egg-info/dependency_links.txt
vec_noise_numpy2.egg-info/requires.txt
vec_noise_numpy2.egg-info/top_level.txt