Metadata-Version: 2.4
Name: vec_noise-numpy2
Version: 1.1.5
Summary: Vectorized Perlin noise for Python
Home-page: https://github.com/zbenjamin/vec_noise
Author: Zev Benjamin
Author-email: zev@strangersgate.com
Classifier: Development Status :: 4 - Beta
Classifier: Topic :: Multimedia :: Graphics
Classifier: License :: OSI Approved :: MIT License
Classifier: Operating System :: MacOS :: MacOS X
Classifier: Operating System :: Microsoft :: Windows
Classifier: Operating System :: POSIX
Classifier: Programming Language :: C
Classifier: Programming Language :: Python :: 2
Classifier: Programming Language :: Python :: 3
License-File: LICENSE.txt
Requires-Dist: numpy<3
Dynamic: author
Dynamic: author-email
Dynamic: classifier
Dynamic: description
Dynamic: home-page
Dynamic: license-file
Dynamic: requires-dist
Dynamic: summary
